[
  {
    "referenceName": "tournament-0",
    "name": "First test tournament",
    "players": [
      "user-stas",
      "user-petro"
    ],
    "game_params": {
      "time_base": 180000
    },
    "tournament_params": {
      "type": "switz",
      "time_begin": "tomorrow"
    },
    "games": [
      {
        "reference": "game-1",
        "round": 2
      }
    ]
  },
  {
    "referenceName": "tournament-1",
    "name": "Second test tournament",
    "players": [
      "user-petro",
      "user-test-login"
    ],
    "game_params": {
      "time_base": 300000
    },
    "tournament_params": {
      "type": "switz",
      "time_begin": "+1hour"
    }
  },
  {
    "referenceName": "tournament-2",
    "name": "Third test tournament",
    "players": [
      "user-stas",
      "user-test-login",
      "user-petro"
    ],
    "game_params": {
      "time_base": 600000
    },
    "tournament_params": {
      "type": "switz",
      "time_begin": "+1minute"
    },
    "games": [
      {
        "reference": "game-from-tournament-2",
        "round": 1
      }
    ],
    "current_round": 1
  },
  {
    "referenceName": "tournament-switz",
    "name": "Test switz tournament even",
    "players": [
      "user-a",
      "user-b",
      "user-c",
      "user-d",
      "user-e",
      "user-f",
      "user-g",
      "user-h",
      "user-i",
      "user-j",
      "user-k",
      "user-l",
      "user-m",
      "user-n",
      "user-o",
      "user-p",
      "user-q",
      "user-r",
      "user-s",
      "user-t",
      "user-u",
      "user-v",
      "user-w",
      "user-x",
      "user-y",
      "user-z",
      "user-test-login"
    ],
    "game_params": {
      "time_base": 600000
    },
    "tournament_params": {
      "type": "switz",
      "time_begin": "+1minute"
    }
  },
  {
    "referenceName": "tournament-switz-even",
    "name": "Test switz tournament odd",
    "players": [
      "user-b",
      "user-c",
      "user-d",
      "user-e",
      "user-f",
      "user-g",
      "user-h",
      "user-i",
      "user-j",
      "user-k",
      "user-l",
      "user-m",
      "user-n",
      "user-o",
      "user-p",
      "user-q",
      "user-r",
      "user-s",
      "user-t",
      "user-u",
      "user-v",
      "user-w",
      "user-x",
      "user-y",
      "user-z"
    ],
    "game_params": {
      "time_base": 600000
    },
    "tournament_params": {
      "type": "switz",
      "time_begin": "+1minute"
    }
  },
  {
    "referenceName": "tournament-round-robin",
    "name": "Round robin test",
    "players": [
      "user-a",
      "user-b",
      "user-c",
      "user-d",
      "user-e",
      "user-f",
      "user-g"
    ],
    "game_params": {
      "time_base": 600000
    },
    "tournament_params": {
      "type": "round_robin",
      "time_begin": "+1minute"
    }
  },
  {
    "referenceName": "tournament-round-robin-current",
    "name": "Round robin test current",
    "players": [
      "user-a",
      "user-b",
      "user-c",
      "user-d",
      "user-e",
      "user-f",
      "user-g"
    ],
    "game_params": {
      "time_base": 600000
    },
    "tournament_params": {
      "type": "round_robin",
      "time_begin": "-1minute"
    },
    "status": "current"
  }
]